<annotation verified="yes">
    <folder>Annotation</folder>
    <filename>IMG_6139.JPG</filename>
    <path>2018-19-FRC-Vision-Labeling-PascalVOC-export/Annotations/IMG_6139.JPG</path>
    <source>
        <database>Unknown</database>
    </source>
    <size>
        <width>4000</width>
        <height>3000</height>
        <depth>3</depth>
    </size>
    <segmented>0</segmented>
    <object>
    <name>Tape</name>
    <pose>Unspecified</pose>
    <truncated>0</truncated>
    <difficult>0</difficult>
    <bndbox>
        <xmin>2955.6451612903224</xmin>
        <ymin>2500</ymin>
        <xmax>3133.064516129032</xmax>
        <ymax>2907.258064516129</ymax>
    </bndbox>
</object><object>
    <name>Tape</name>
    <pose>Unspecified</pose>
    <truncated>0</truncated>
    <difficult>0</difficult>
    <bndbox>
        <xmin>2286.2903225806454</xmin>
        <ymin>2669.3548387096776</ymin>
        <xmax>2512.0967741935488</xmax>
        <ymax>3000</ymax>
    </bndbox>
</object>
</annotation>
